jsonschemax/__init__.py
jsonschemax/compilation.py
jsonschemax/errors.py
jsonschemax/keywords.py
jsonschemax/meta_validation.py
jsonschemax/types.py
jsonschemax/uri.py
jsonschemax/utils.py
jsonschemax/meta_schemas/__init__.py
jsonschemax-0.0.2.dist-info/LICENSE
jsonschemax-0.0.2.dist-info/METADATA
jsonschemax-0.0.2.dist-info/WHEEL
jsonschemax-0.0.2.dist-info/top_level.txt
jsonschemax-0.0.2.dist-info/RECORD
