Metadata-Version: 2.1
Name: jsonschemax
Version: 0.0.2
Summary: An implementation of JSON Schema for Python
Home-page: https://github.com/ocavue/jsonschemax
Author: ocavue
Author-email: ocavue@gmail.com
License: UNKNOWN
Platform: UNKNOWN
Classifier: Programming Language :: Python :: 3.7
Classifier: License :: OSI Approved :: MIT License
Classifier: Operating System :: OS Independent
